desktop_agent/__init__.py
desktop_agent/__main__.py
desktop_agent/commands/__init__.py
desktop_agent/commands/app.py
desktop_agent/commands/keyboard.py
desktop_agent/commands/message.py
desktop_agent/commands/mouse.py
desktop_agent/commands/screen.py
desktop_agent/specs/__init__.py
desktop_agent/specs/v1/schema.json
desktop_agent/utils/__init__.py
desktop_agent/utils/errors.py
desktop_agent/utils/response.py
desktop_agent-1.3.1.dist-info/METADATA
desktop_agent-1.3.1.dist-info/WHEEL
desktop_agent-1.3.1.dist-info/entry_points.txt
desktop_agent-1.3.1.dist-info/RECORD
