Metadata-Version: 2.4
Name: desktop-agent
Version: 1.3.1
Summary: AI agent skill for desktop automation using PyAutoGUI
Author: Patrick Porto
Keywords: agent,ai,automation,desktop,pyautogui,skill
Classifier: Development Status :: 4 - Beta
Classifier: Intended Audience :: Developers
Classifier: Programming Language :: Python :: 3.12
Classifier: Topic :: Software Development :: Libraries :: Python Modules
Requires-Python: >=3.12
Requires-Dist: easyocr>=1.7.2
Requires-Dist: opencv-python>=4.13.0.90
Requires-Dist: pillow>=12.1.0
Requires-Dist: pyautogui>=0.9.54
Requires-Dist: pydantic>=2.0.0
Requires-Dist: pywinctl>=0.4.1
Requires-Dist: typer>=0.21.1
